[
  {
    "book": "MIC",
    "chapter": 1,
    "verse": 1,
    "content": [
      {
        "text": "Yahweh’s",
        "foot": {
          "type": "stu",
          "content": "“Yahweh” is God’s proper Name, sometimes rendered “LORD” (all caps) in other translations."
        },
        "paragraph": true
      },
      {
        "text": " word that came to Micah of Morasheth in the days of Jotham, Ahaz, and Hezekiah, kings of Judah, which he saw concerning Samaria and Jerusalem.",
        "break": true
      }
    ]
  },
  {
    "book": "MIC",
    "chapter": 1,
    "verse": 2,
    "content": [
      {
        "text": "Hear, you peoples, all of you!",
        "break": true
      },
      {
        "text": "Listen, O earth, and all that is therein.",
        "break": true
      },
      {
        "text": "Let the Lord",
        "foot": {
          "type": "trn",
          "content": "The word translated “Lord” is “Adonai.”"
        }
      },
      {
        "text": " Yahweh be witness against you,",
        "break": true
      },
      {
        "text": "the Lord from his holy temple.",
        "break": true
      }
    ]
  },
  {
    "book": "MIC",
    "chapter": 1,
    "verse": 3,
    "content": [
      {
        "text": "For behold,",
        "foot": {
          "type": "trn",
          "content": [
            "“Behold”, from “",
            {
              "text": "הִנֵּה",
              "script": "H"
            },
            "”, means look at, take notice, observe, see, or gaze at. It is often used as an interjection."
          ]
        }
      },
      {
        "text": " Yahweh comes out of his place,",
        "break": true
      },
      {
        "text": "and will come down and tread on the high places of the earth.",
        "break": true
      }
    ]
  },
  {
    "book": "MIC",
    "chapter": 1,
    "verse": 4,
    "content": [
      {
        "text": "The mountains melt under him,",
        "break": true
      },
      {
        "text": "and the valleys split apart like wax before the fire,",
        "break": true
      },
      "like waters that are poured down a steep place."
    ]
  },
  {
    "book": "MIC",
    "chapter": 1,
    "verse": 5,
    "content": [
      {
        "text": "“All this is for the disobedience of Jacob,",
        "paragraph": true,
        "break": true
      },
      {
        "text": "and for the sins of the house of Israel.",
        "break": true
      },
      {
        "text": "What is the disobedience of Jacob?",
        "break": true
      },
      {
        "text": "Isn’t it Samaria?",
        "break": true
      },
      {
        "text": "And what are the high places of Judah?",
        "break": true
      },
      {
        "text": "Aren’t they Jerusalem?",
        "break": true
      }
    ]
  },
  {
    "book": "MIC",
    "chapter": 1,
    "verse": 6,
    "content": [
      {
        "text": "Therefore I will make Samaria like a rubble heap of the field,",
        "break": true
      },
      {
        "text": "like places for planting vineyards;",
        "break": true
      },
      {
        "text": "and I will pour down its stones into the valley,",
        "break": true
      },
      {
        "text": "and I will uncover its foundations.",
        "break": true
      }
    ]
  },
  {
    "book": "MIC",
    "chapter": 1,
    "verse": 7,
    "content": [
      {
        "text": "All her idols will be beaten to pieces,",
        "break": true
      },
      {
        "text": "all her temple gifts will be burned with fire,",
        "break": true
      },
      {
        "text": "and I will destroy all her images;",
        "break": true
      },
      {
        "text": "for of the hire of a prostitute has she gathered them,",
        "break": true
      },
      "and to the hire of a prostitute shall they return.”"
    ]
  },
  {
    "book": "MIC",
    "chapter": 1,
    "verse": 8,
    "content": [
      {
        "text": "For this I will lament and wail.",
        "paragraph": true,
        "break": true
      },
      {
        "text": "I will go stripped and naked.",
        "break": true
      },
      {
        "text": "I will howl like the jackals",
        "break": true
      },
      {
        "text": "and mourn like the ostriches.",
        "break": true
      }
    ]
  },
  {
    "book": "MIC",
    "chapter": 1,
    "verse": 9,
    "content": [
      {
        "text": "For her wounds are incurable;",
        "break": true
      },
      {
        "text": "for it has come even to Judah.",
        "break": true
      },
      {
        "text": "It reaches to the gate of my people,",
        "break": true
      },
      {
        "text": "even to Jerusalem.",
        "break": true
      }
    ]
  },
  {
    "book": "MIC",
    "chapter": 1,
    "verse": 10,
    "content": [
      {
        "text": "Don’t tell it in Gath.",
        "break": true
      },
      {
        "text": "Don’t weep at all.",
        "break": true
      },
      {
        "text": "At Beth Ophrah",
        "foot": {
          "type": "stu",
          "content": "Beth Ophrah means literally “House of Dust.”"
        }
      },
      {
        "text": " I have rolled myself in the dust.",
        "break": true
      }
    ]
  },
  {
    "book": "MIC",
    "chapter": 1,
    "verse": 11,
    "content": [
      {
        "text": "Pass on, inhabitant of Shaphir, in nakedness and shame.",
        "break": true
      },
      {
        "text": "The inhabitant of Zaanan won’t come out.",
        "break": true
      },
      {
        "text": "The wailing of Beth Ezel will take from you his protection.",
        "break": true
      }
    ]
  },
  {
    "book": "MIC",
    "chapter": 1,
    "verse": 12,
    "content": [
      {
        "text": "For the inhabitant of Maroth waits anxiously for good,",
        "break": true
      },
      {
        "text": "because evil has come down from Yahweh to the gate of Jerusalem.",
        "break": true
      }
    ]
  },
  {
    "book": "MIC",
    "chapter": 1,
    "verse": 13,
    "content": [
      {
        "text": "Harness the chariot to the swift steed, inhabitant of Lachish.",
        "break": true
      },
      {
        "text": "She was the beginning of sin to the daughter of Zion;",
        "break": true
      },
      {
        "text": "for the transgressions of Israel were found in you.",
        "break": true
      }
    ]
  },
  {
    "book": "MIC",
    "chapter": 1,
    "verse": 14,
    "content": [
      {
        "text": "Therefore you will give a parting gift to Moresheth Gath.",
        "break": true
      },
      {
        "text": "The houses of Achzib will be a deceitful thing to the kings of Israel.",
        "break": true
      }
    ]
  },
  {
    "book": "MIC",
    "chapter": 1,
    "verse": 15,
    "content": [
      {
        "text": "I will yet bring a conqueror to you, inhabitants of Mareshah.",
        "break": true
      },
      {
        "text": "The glory of Israel will come to Adullam.",
        "break": true
      }
    ]
  },
  {
    "book": "MIC",
    "chapter": 1,
    "verse": 16,
    "content": [
      {
        "text": "Shave your heads,",
        "break": true
      },
      {
        "text": "and cut off your hair for the children of your delight.",
        "break": true
      },
      {
        "text": "Enlarge your baldness like the vulture,",
        "break": true
      },
      "for they have gone into captivity from you!"
    ]
  },
  {
    "book": "MIC",
    "chapter": 2,
    "verse": 1,
    "content": [
      {
        "text": "Woe to those who devise iniquity",
        "paragraph": true,
        "break": true
      },
      {
        "text": "and work evil on their beds!",
        "break": true
      },
      {
        "text": "When the morning is light, they practice it,",
        "break": true
      },
      {
        "text": "because it is in the power of their hand.",
        "break": true
      }
    ]
  },
  {
    "book": "MIC",
    "chapter": 2,
    "verse": 2,
    "content": [
      {
        "text": "They covet fields and seize them,",
        "break": true
      },
      {
        "text": "and houses, then take them away.",
        "break": true
      },
      {
        "text": "They oppress a man and his house,",
        "break": true
      },
      {
        "text": "even a man and his heritage.",
        "break": true
      }
    ]
  },
  {
    "book": "MIC",
    "chapter": 2,
    "verse": 3,
    "content": [
      {
        "text": "Therefore Yahweh says:",
        "break": true
      },
      {
        "text": "“Behold, I am planning against these people a disaster,",
        "break": true
      },
      {
        "text": "from which you will not remove your necks,",
        "break": true
      },
      {
        "text": "neither will you walk haughtily,",
        "break": true
      },
      {
        "text": "for it is an evil time.",
        "break": true
      }
    ]
  },
  {
    "book": "MIC",
    "chapter": 2,
    "verse": 4,
    "content": [
      {
        "text": "In that day they will take up a parable against you,",
        "break": true
      },
      {
        "text": "and lament with a doleful lamentation, saying,",
        "break": true
      },
      {
        "text": "‘We are utterly ruined!",
        "break": true
      },
      {
        "text": "My people’s possession is divided up.",
        "break": true
      },
      {
        "text": "Indeed he takes it from me and assigns our fields to traitors!’ ”",
        "break": true
      }
    ]
  },
  {
    "book": "MIC",
    "chapter": 2,
    "verse": 5,
    "content": {
      "text": "Therefore you will have no one who divides the land by lot in Yahweh’s assembly.",
      "break": true
    }
  },
  {
    "book": "MIC",
    "chapter": 2,
    "verse": 6,
    "content": [
      {
        "text": "“Don’t prophesy!”—they prophesy—",
        "break": true
      },
      {
        "text": "“Don’t prophesy about these things.",
        "break": true
      },
      {
        "text": "Disgrace won’t overtake us.”",
        "break": true
      }
    ]
  },
  {
    "book": "MIC",
    "chapter": 2,
    "verse": 7,
    "content": [
      {
        "text": "Shall it be said, O house of Jacob,",
        "break": true
      },
      {
        "text": "“Is Yahweh’s Spirit angry?",
        "break": true
      },
      {
        "text": "Are these his doings?",
        "break": true
      },
      {
        "text": "Don’t my words do good to him who walks blamelessly?”",
        "break": true
      }
    ]
  },
  {
    "book": "MIC",
    "chapter": 2,
    "verse": 8,
    "content": [
      {
        "text": "But lately my people have risen up as an enemy.",
        "break": true
      },
      {
        "text": "You strip the robe and clothing from those who pass by without a care, returning from battle.",
        "break": true
      }
    ]
  },
  {
    "book": "MIC",
    "chapter": 2,
    "verse": 9,
    "content": [
      {
        "text": "You drive the women of my people out from their pleasant houses;",
        "break": true
      },
      {
        "text": "from their young children you take away my blessing forever.",
        "break": true
      }
    ]
  },
  {
    "book": "MIC",
    "chapter": 2,
    "verse": 10,
    "content": [
      {
        "text": "Arise, and depart!",
        "break": true
      },
      {
        "text": "For this is not your resting place,",
        "break": true
      },
      {
        "text": "because of uncleanness that destroys,",
        "break": true
      },
      {
        "text": "even with a grievous destruction.",
        "break": true
      }
    ]
  },
  {
    "book": "MIC",
    "chapter": 2,
    "verse": 11,
    "content": [
      {
        "text": "If a man walking in a spirit of falsehood lies, saying,",
        "break": true
      },
      {
        "text": "“I will prophesy to you of wine and of strong drink,”",
        "break": true
      },
      {
        "text": "he would be the prophet of this people.",
        "break": true
      }
    ]
  },
  {
    "book": "MIC",
    "chapter": 2,
    "verse": 12,
    "content": [
      {
        "text": "I will surely assemble all of you, Jacob.",
        "break": true
      },
      {
        "text": "I will surely gather the remnant of Israel.",
        "break": true
      },
      {
        "text": "I will put them together as the sheep of Bozrah,",
        "break": true
      },
      {
        "text": "as a flock in the middle of their pasture.",
        "break": true
      },
      {
        "text": "They will swarm with people.",
        "break": true
      }
    ]
  },
  {
    "book": "MIC",
    "chapter": 2,
    "verse": 13,
    "content": [
      {
        "text": "He who breaks open the way goes up before them.",
        "break": true
      },
      {
        "text": "They break through the gate, and go out.",
        "break": true
      },
      {
        "text": "Their king passes on before them,",
        "break": true
      },
      "with Yahweh at their head."
    ]
  },
  {
    "book": "MIC",
    "chapter": 3,
    "verse": 1,
    "content": [
      {
        "text": "I said,",
        "paragraph": true,
        "break": true
      },
      {
        "text": "“Please listen, you heads of Jacob,",
        "break": true
      },
      {
        "text": "and rulers of the house of Israel:",
        "break": true
      },
      {
        "text": "Isn’t it for you to know justice?",
        "break": true
      }
    ]
  },
  {
    "book": "MIC",
    "chapter": 3,
    "verse": 2,
    "content": [
      {
        "text": "You who hate the good,",
        "break": true
      },
      {
        "text": "and love the evil;",
        "break": true
      },
      {
        "text": "who tear off their skin,",
        "break": true
      },
      {
        "text": "and their flesh from off their bones;",
        "break": true
      }
    ]
  },
  {
    "book": "MIC",
    "chapter": 3,
    "verse": 3,
    "content": [
      {
        "text": "who also eat the flesh of my people,",
        "break": true
      },
      {
        "text": "and peel their skin from off them,",
        "break": true
      },
      {
        "text": "and break their bones,",
        "break": true
      },
      {
        "text": "and chop them in pieces, as for the pot,",
        "break": true
      },
      {
        "text": "and as meat within the cauldron.",
        "break": true
      }
    ]
  },
  {
    "book": "MIC",
    "chapter": 3,
    "verse": 4,
    "content": [
      {
        "text": "Then they will cry to Yahweh,",
        "break": true
      },
      {
        "text": "but he will not answer them.",
        "break": true
      },
      {
        "text": "Yes, he will hide his face from them at that time,",
        "break": true
      },
      "because they made their deeds evil.”"
    ]
  },
  {
    "book": "MIC",
    "chapter": 3,
    "verse": 5,
    "content": {
      "text": "Yahweh says concerning the prophets who lead my people astray—for those who feed their teeth, they proclaim, “Peace!” and whoever doesn’t provide for their mouths, they prepare war against him:",
      "paragraph": true,
      "break": true
    }
  },
  {
    "book": "MIC",
    "chapter": 3,
    "verse": 6,
    "content": [
      {
        "text": "“Therefore night is over you, with no vision,",
        "break": true
      },
      {
        "text": "and it is dark to you, that you may not divine;",
        "break": true
      },
      {
        "text": "and the sun will go down on the prophets,",
        "break": true
      },
      {
        "text": "and the day will be black over them.",
        "break": true
      }
    ]
  },
  {
    "book": "MIC",
    "chapter": 3,
    "verse": 7,
    "content": [
      {
        "text": "The seers shall be disappointed,",
        "break": true
      },
      {
        "text": "and the diviners confounded.",
        "break": true
      },
      {
        "text": "Yes, they shall all cover their lips,",
        "break": true
      },
      {
        "text": "for there is no answer from God.”",
        "foot": {
          "type": "trn",
          "content": [
            "The Hebrew word rendered “God” is “",
            {
              "text": "אֱלֹהִ֑ים",
              "script": "H"
            },
            "” (Elohim)."
          ]
        },
        "break": true
      }
    ]
  },
  {
    "book": "MIC",
    "chapter": 3,
    "verse": 8,
    "content": [
      {
        "text": "But as for me, I am full of power by Yahweh’s Spirit,",
        "break": true
      },
      {
        "text": "and of judgment, and of might,",
        "break": true
      },
      {
        "text": "to declare to Jacob his disobedience,",
        "break": true
      },
      {
        "text": "and to Israel his sin.",
        "break": true
      }
    ]
  },
  {
    "book": "MIC",
    "chapter": 3,
    "verse": 9,
    "content": [
      {
        "text": "Please listen to this, you heads of the house of Jacob,",
        "break": true
      },
      {
        "text": "and rulers of the house of Israel,",
        "break": true
      },
      {
        "text": "who abhor justice,",
        "break": true
      },
      {
        "text": "and pervert all equity,",
        "break": true
      }
    ]
  },
  {
    "book": "MIC",
    "chapter": 3,
    "verse": 10,
    "content": [
      {
        "text": "who build up Zion with blood,",
        "break": true
      },
      {
        "text": "and Jerusalem with iniquity.",
        "break": true
      }
    ]
  },
  {
    "book": "MIC",
    "chapter": 3,
    "verse": 11,
    "content": [
      {
        "text": "Her leaders judge for bribes,",
        "break": true
      },
      {
        "text": "and her priests teach for a price,",
        "break": true
      },
      {
        "text": "and her prophets of it tell fortunes for money;",
        "break": true
      },
      {
        "text": "yet they lean on Yahweh, and say,",
        "break": true
      },
      {
        "text": "“Isn’t Yahweh among us?",
        "break": true
      },
      {
        "text": "No disaster will come on us.”",
        "break": true
      }
    ]
  },
  {
    "book": "MIC",
    "chapter": 3,
    "verse": 12,
    "content": [
      {
        "text": "Therefore Zion for your sake will be plowed like a field,",
        "break": true
      },
      {
        "text": "and Jerusalem will become heaps of rubble,",
        "break": true
      },
      "and the mountain of the temple like the high places of a forest."
    ]
  },
  {
    "book": "MIC",
    "chapter": 4,
    "verse": 1,
    "content": [
      {
        "text": "But in the latter days,",
        "paragraph": true,
        "break": true
      },
      {
        "text": "it will happen that the mountain of Yahweh’s temple will be established on the top of the mountains,",
        "break": true
      },
      {
        "text": "and it will be exalted above the hills;",
        "break": true
      },
      {
        "text": "and peoples will stream to it.",
        "break": true
      }
    ]
  },
  {
    "book": "MIC",
    "chapter": 4,
    "verse": 2,
    "content": [
      {
        "text": "Many nations will go and say,",
        "break": true
      },
      {
        "text": "“Come! Let’s go up to the mountain of Yahweh,",
        "break": true
      },
      {
        "text": "and to the house of the God of Jacob;",
        "break": true
      },
      {
        "text": "and he will teach us of his ways,",
        "break": true
      },
      {
        "text": "and we will walk in his paths.”",
        "break": true
      },
      {
        "text": "For the law will go out of Zion,",
        "break": true
      },
      {
        "text": "and Yahweh’s word from Jerusalem;",
        "break": true
      }
    ]
  },
  {
    "book": "MIC",
    "chapter": 4,
    "verse": 3,
    "content": [
      {
        "text": "and he will judge between many peoples,",
        "break": true
      },
      {
        "text": "and will decide concerning strong nations afar off.",
        "break": true
      },
      {
        "text": "They will beat their swords into plowshares,",
        "break": true
      },
      {
        "text": "and their spears into pruning hooks.",
        "break": true
      },
      {
        "text": "Nation will not lift up sword against nation,",
        "break": true
      },
      {
        "text": "neither will they learn war any more.",
        "break": true
      }
    ]
  },
  {
    "book": "MIC",
    "chapter": 4,
    "verse": 4,
    "content": [
      {
        "text": "But every man will sit under his vine and under his fig tree.",
        "break": true
      },
      {
        "text": "No one will make them afraid,",
        "break": true
      },
      "for the mouth of Yahweh of Armies has spoken."
    ]
  },
  {
    "book": "MIC",
    "chapter": 4,
    "verse": 5,
    "content": [
      {
        "text": "Indeed all the nations may walk in the name of their gods,",
        "break": true
      },
      {
        "text": "but we will walk in the name of Yahweh our God forever and ever.",
        "break": true
      }
    ]
  },
  {
    "book": "MIC",
    "chapter": 4,
    "verse": 6,
    "content": [
      {
        "text": "“In that day,” says Yahweh,",
        "break": true
      },
      {
        "text": "“I will assemble that which is lame,",
        "break": true
      },
      {
        "text": "and I will gather that which is driven away,",
        "break": true
      },
      {
        "text": "and that which I have afflicted;",
        "break": true
      }
    ]
  },
  {
    "book": "MIC",
    "chapter": 4,
    "verse": 7,
    "content": [
      {
        "text": "and I will make that which was lame a remnant,",
        "break": true
      },
      {
        "text": "and that which was cast far off a strong nation:",
        "break": true
      },
      {
        "text": "and Yahweh will reign over them on Mount Zion from then on, even forever.”",
        "break": true
      }
    ]
  },
  {
    "book": "MIC",
    "chapter": 4,
    "verse": 8,
    "content": [
      {
        "text": "You, tower of the flock, the hill of the daughter of Zion,",
        "break": true
      },
      {
        "text": "to you it will come.",
        "break": true
      },
      {
        "text": "Yes, the former dominion will come,",
        "break": true
      },
      "the kingdom of the daughter of Jerusalem."
    ]
  },
  {
    "book": "MIC",
    "chapter": 4,
    "verse": 9,
    "content": [
      {
        "text": "Now why do you cry out aloud?",
        "paragraph": true,
        "break": true
      },
      {
        "text": "Is there no king in you?",
        "break": true
      },
      {
        "text": "Has your counselor perished,",
        "break": true
      },
      {
        "text": "that pains have taken hold of you as of a woman in travail?",
        "break": true
      }
    ]
  },
  {
    "book": "MIC",
    "chapter": 4,
    "verse": 10,
    "content": [
      {
        "text": "Be in pain, and labor to give birth, daughter of Zion,",
        "break": true
      },
      {
        "text": "like a woman in travail;",
        "break": true
      },
      {
        "text": "for now you will go out of the city,",
        "break": true
      },
      {
        "text": "and will dwell in the field,",
        "break": true
      },
      {
        "text": "and will come even to Babylon.",
        "break": true
      },
      {
        "text": "There you will be rescued.",
        "break": true
      },
      "There Yahweh will redeem you from the hand of your enemies."
    ]
  },
  {
    "book": "MIC",
    "chapter": 4,
    "verse": 11,
    "content": [
      {
        "text": "Now many nations have assembled against you, that say,",
        "paragraph": true,
        "break": true
      },
      {
        "text": "“Let her be defiled,",
        "break": true
      },
      {
        "text": "and let our eye gloat over Zion.”",
        "break": true
      }
    ]
  },
  {
    "book": "MIC",
    "chapter": 4,
    "verse": 12,
    "content": [
      {
        "text": "But they don’t know the thoughts of Yahweh,",
        "break": true
      },
      {
        "text": "neither do they understand his counsel;",
        "break": true
      },
      {
        "text": "for he has gathered them like the sheaves to the threshing floor.",
        "break": true
      }
    ]
  },
  {
    "book": "MIC",
    "chapter": 4,
    "verse": 13,
    "content": [
      {
        "text": "Arise and thresh, daughter of Zion,",
        "break": true
      },
      {
        "text": "for I will make your horn iron,",
        "break": true
      },
      {
        "text": "and I will make your hoofs bronze.",
        "break": true
      },
      {
        "text": "You will beat in pieces many peoples.",
        "break": true
      },
      {
        "text": "I will devote their gain to Yahweh,",
        "break": true
      },
      "and their substance to the Lord of the whole earth."
    ]
  },
  {
    "book": "MIC",
    "chapter": 5,
    "verse": 1,
    "content": [
      {
        "text": "Now you shall gather yourself in troops,",
        "paragraph": true,
        "break": true
      },
      {
        "text": "daughter of troops.",
        "break": true
      },
      {
        "text": "He has laid siege against us.",
        "break": true
      },
      {
        "text": "They will strike the judge of Israel with a rod on the cheek.",
        "break": true
      }
    ]
  },
  {
    "book": "MIC",
    "chapter": 5,
    "verse": 2,
    "content": [
      {
        "text": "But you, Bethlehem Ephrathah,",
        "break": true
      },
      {
        "text": "being small among the clans of Judah,",
        "break": true
      },
      {
        "text": "out of you one will come out to me who is to be ruler in Israel;",
        "break": true
      },
      {
        "text": "whose goings out are from of old, from ancient times.",
        "break": true
      }
    ]
  },
  {
    "book": "MIC",
    "chapter": 5,
    "verse": 3,
    "content": [
      {
        "text": "Therefore he will abandon them until the time that she who is in labor gives birth.",
        "break": true
      },
      {
        "text": "Then the rest of his brothers will return to the children of Israel.",
        "break": true
      }
    ]
  },
  {
    "book": "MIC",
    "chapter": 5,
    "verse": 4,
    "content": [
      {
        "text": "He shall stand, and shall shepherd in the strength of Yahweh,",
        "break": true
      },
      {
        "text": "in the majesty of the name of Yahweh his God.",
        "break": true
      },
      {
        "text": "They will live, for then he will be great to the ends of the earth.",
        "break": true
      }
    ]
  },
  {
    "book": "MIC",
    "chapter": 5,
    "verse": 5,
    "content": [
      {
        "text": "He will be our peace when Assyria invades our land",
        "break": true
      },
      {
        "text": "and when he marches through our fortresses,",
        "break": true
      },
      {
        "text": "then we will raise against him seven shepherds,",
        "break": true
      },
      {
        "text": "and eight leaders of men.",
        "break": true
      }
    ]
  },
  {
    "book": "MIC",
    "chapter": 5,
    "verse": 6,
    "content": [
      {
        "text": "They will rule the land of Assyria with the sword,",
        "break": true
      },
      {
        "text": "and the land of Nimrod in its gates.",
        "break": true
      },
      {
        "text": "He will deliver us from the Assyrian,",
        "break": true
      },
      {
        "text": "when he invades our land,",
        "break": true
      },
      {
        "text": "and when he marches within our border.",
        "break": true
      }
    ]
  },
  {
    "book": "MIC",
    "chapter": 5,
    "verse": 7,
    "content": [
      {
        "text": "The remnant of Jacob will be among many peoples",
        "break": true
      },
      {
        "text": "like dew from Yahweh,",
        "break": true
      },
      {
        "text": "like showers on the grass,",
        "break": true
      },
      {
        "text": "that don’t wait for man",
        "break": true
      },
      {
        "text": "nor wait for the sons of men.",
        "break": true
      }
    ]
  },
  {
    "book": "MIC",
    "chapter": 5,
    "verse": 8,
    "content": [
      {
        "text": "The remnant of Jacob will be among the nations,",
        "break": true
      },
      {
        "text": "among many peoples,",
        "break": true
      },
      {
        "text": "like a lion among the animals of the forest,",
        "break": true
      },
      {
        "text": "like a young lion among the flocks of sheep;",
        "break": true
      },
      {
        "text": "who, if he goes through, treads down and tears in pieces,",
        "break": true
      },
      {
        "text": "and there is no one to deliver.",
        "break": true
      }
    ]
  },
  {
    "book": "MIC",
    "chapter": 5,
    "verse": 9,
    "content": [
      {
        "text": "Let your hand be lifted up above your adversaries,",
        "break": true
      },
      {
        "text": "and let all of your enemies be cut off.",
        "break": true
      }
    ]
  },
  {
    "book": "MIC",
    "chapter": 5,
    "verse": 10,
    "content": [
      {
        "text": "“It will happen in that day”, says Yahweh,",
        "break": true
      },
      {
        "text": "“that I will cut off your horses from among you",
        "break": true
      },
      {
        "text": "and will destroy your chariots.",
        "break": true
      }
    ]
  },
  {
    "book": "MIC",
    "chapter": 5,
    "verse": 11,
    "content": [
      {
        "text": "I will cut off the cities of your land",
        "break": true
      },
      {
        "text": "and will tear down all your strongholds.",
        "break": true
      }
    ]
  },
  {
    "book": "MIC",
    "chapter": 5,
    "verse": 12,
    "content": [
      {
        "text": "I will destroy witchcraft from your hand.",
        "break": true
      },
      {
        "text": "You shall have no soothsayers.",
        "break": true
      }
    ]
  },
  {
    "book": "MIC",
    "chapter": 5,
    "verse": 13,
    "content": [
      {
        "text": "I will cut off your engraved images and your pillars from among you;",
        "break": true
      },
      {
        "text": "and you shall no more worship the work of your hands.",
        "break": true
      }
    ]
  },
  {
    "book": "MIC",
    "chapter": 5,
    "verse": 14,
    "content": [
      {
        "text": "I will uproot your Asherah poles from among you;",
        "break": true
      },
      {
        "text": "and I will destroy your cities.",
        "break": true
      }
    ]
  },
  {
    "book": "MIC",
    "chapter": 5,
    "verse": 15,
    "content": [
      {
        "text": "I will execute vengeance in anger",
        "break": true
      },
      "and wrath on the nations that didn’t listen.”"
    ]
  },
  {
    "book": "MIC",
    "chapter": 6,
    "verse": 1,
    "content": [
      {
        "text": "Listen now to what Yahweh says:",
        "paragraph": true,
        "break": true
      },
      {
        "text": "“Arise, plead your case before the mountains,",
        "break": true
      },
      {
        "text": "and let the hills hear what you have to say.",
        "break": true
      }
    ]
  },
  {
    "book": "MIC",
    "chapter": 6,
    "verse": 2,
    "content": [
      {
        "text": "Hear, you mountains, Yahweh’s indictment,",
        "break": true
      },
      {
        "text": "and you enduring foundations of the earth;",
        "break": true
      },
      {
        "text": "for Yahweh has a case against his people,",
        "break": true
      },
      {
        "text": "and he will contend with Israel.",
        "break": true
      }
    ]
  },
  {
    "book": "MIC",
    "chapter": 6,
    "verse": 3,
    "content": [
      {
        "text": "My people, what have I done to you?",
        "break": true
      },
      {
        "text": "How have I burdened you?",
        "break": true
      },
      {
        "text": "Answer me!",
        "break": true
      }
    ]
  },
  {
    "book": "MIC",
    "chapter": 6,
    "verse": 4,
    "content": [
      {
        "text": "For I brought you up out of the land of Egypt,",
        "break": true
      },
      {
        "text": "and redeemed you out of the house of bondage.",
        "break": true
      },
      {
        "text": "I sent before you Moses, Aaron, and Miriam.",
        "break": true
      }
    ]
  },
  {
    "book": "MIC",
    "chapter": 6,
    "verse": 5,
    "content": [
      {
        "text": "My people, remember now what Balak king of Moab devised,",
        "break": true
      },
      {
        "text": "and what Balaam the son of Beor answered him from Shittim to Gilgal,",
        "break": true
      },
      "that you may know the righteous acts of Yahweh.”"
    ]
  },
  {
    "book": "MIC",
    "chapter": 6,
    "verse": 6,
    "content": [
      {
        "text": "How shall I come before Yahweh,",
        "paragraph": true,
        "break": true
      },
      {
        "text": "and bow myself before the exalted God?",
        "break": true
      },
      {
        "text": "Shall I come before him with burnt offerings,",
        "break": true
      },
      {
        "text": "with calves a year old?",
        "break": true
      }
    ]
  },
  {
    "book": "MIC",
    "chapter": 6,
    "verse": 7,
    "content": [
      {
        "text": "Will Yahweh be pleased with thousands of rams?",
        "break": true
      },
      {
        "text": "With tens of thousands of rivers of oil?",
        "break": true
      },
      {
        "text": "Shall I give my firstborn for my disobedience?",
        "break": true
      },
      {
        "text": "The fruit of my body for the sin of my soul?",
        "break": true
      }
    ]
  },
  {
    "book": "MIC",
    "chapter": 6,
    "verse": 8,
    "content": [
      {
        "text": "He has shown you, O man, what is good.",
        "break": true
      },
      {
        "text": "What does Yahweh require of you, but to act justly,",
        "break": true
      },
      "to love mercy, and to walk humbly with your God?"
    ]
  },
  {
    "book": "MIC",
    "chapter": 6,
    "verse": 9,
    "content": [
      {
        "text": "Yahweh’s voice calls to the city—",
        "paragraph": true,
        "break": true
      },
      {
        "text": "and wisdom fears your name—",
        "break": true
      },
      {
        "text": "“Listen to the rod,",
        "break": true
      },
      {
        "text": "and he who appointed it.",
        "break": true
      }
    ]
  },
  {
    "book": "MIC",
    "chapter": 6,
    "verse": 10,
    "content": [
      {
        "text": "Are there yet treasures of wickedness in the house of the wicked,",
        "break": true
      },
      {
        "text": "and a short ephah",
        "foot": {
          "type": "stu",
          "content": "An ephah is a measure of volume (about 22 liters or about 2/3 of a bushel), and a short ephah is made smaller than a full ephah for the purpose of cheating customers."
        }
      },
      {
        "text": " that is accursed?",
        "break": true
      }
    ]
  },
  {
    "book": "MIC",
    "chapter": 6,
    "verse": 11,
    "content": [
      {
        "text": "Shall I tolerate dishonest scales,",
        "break": true
      },
      {
        "text": "and a bag of deceitful weights?",
        "break": true
      }
    ]
  },
  {
    "book": "MIC",
    "chapter": 6,
    "verse": 12,
    "content": [
      {
        "text": "Her rich men are full of violence,",
        "break": true
      },
      {
        "text": "her inhabitants speak lies,",
        "break": true
      },
      {
        "text": "and their tongue is deceitful in their speech.",
        "break": true
      }
    ]
  },
  {
    "book": "MIC",
    "chapter": 6,
    "verse": 13,
    "content": [
      {
        "text": "Therefore I also have struck you with a grievous wound.",
        "break": true
      },
      {
        "text": "I have made you desolate because of your sins.",
        "break": true
      }
    ]
  },
  {
    "book": "MIC",
    "chapter": 6,
    "verse": 14,
    "content": [
      {
        "text": "You shall eat, but not be satisfied.",
        "break": true
      },
      {
        "text": "Your hunger will be within you.",
        "break": true
      },
      {
        "text": "You will store up, but not save,",
        "break": true
      },
      {
        "text": "and that which you save I will give up to the sword.",
        "break": true
      }
    ]
  },
  {
    "book": "MIC",
    "chapter": 6,
    "verse": 15,
    "content": [
      {
        "text": "You will sow, but won’t reap.",
        "break": true
      },
      {
        "text": "You will tread the olives, but won’t anoint yourself with oil;",
        "break": true
      },
      {
        "text": "and crush grapes, but won’t drink the wine.",
        "break": true
      }
    ]
  },
  {
    "book": "MIC",
    "chapter": 6,
    "verse": 16,
    "content": [
      {
        "text": "For the statutes of Omri are kept,",
        "break": true
      },
      {
        "text": "and all the works of Ahab’s house.",
        "break": true
      },
      {
        "text": "You walk in their counsels,",
        "break": true
      },
      {
        "text": "that I may make you a ruin,",
        "break": true
      },
      {
        "text": "and your inhabitants a hissing.",
        "break": true
      },
      "You will bear the reproach of my people.”"
    ]
  },
  {
    "book": "MIC",
    "chapter": 7,
    "verse": 1,
    "content": [
      {
        "text": "Misery is mine!",
        "paragraph": true,
        "break": true
      },
      {
        "text": "Indeed, I am like one who gathers the summer fruits, as gleanings of the vineyard.",
        "break": true
      },
      {
        "text": "There is no cluster of grapes to eat.",
        "break": true
      },
      {
        "text": "My soul desires to eat the early fig.",
        "break": true
      }
    ]
  },
  {
    "book": "MIC",
    "chapter": 7,
    "verse": 2,
    "content": [
      {
        "text": "The godly man has perished out of the earth,",
        "break": true
      },
      {
        "text": "and there is no one upright among men.",
        "break": true
      },
      {
        "text": "They all lie in wait for blood;",
        "break": true
      },
      {
        "text": "every man hunts his brother with a net.",
        "break": true
      }
    ]
  },
  {
    "book": "MIC",
    "chapter": 7,
    "verse": 3,
    "content": [
      {
        "text": "Their hands are on that which is evil to do it diligently.",
        "break": true
      },
      {
        "text": "The ruler and judge ask for a bribe.",
        "break": true
      },
      {
        "text": "The powerful man dictates the evil desire of his soul.",
        "break": true
      },
      {
        "text": "Thus they conspire together.",
        "break": true
      }
    ]
  },
  {
    "book": "MIC",
    "chapter": 7,
    "verse": 4,
    "content": [
      {
        "text": "The best of them is like a brier.",
        "break": true
      },
      {
        "text": "The most upright is worse than a thorn hedge.",
        "break": true
      },
      {
        "text": "The day of your watchmen,",
        "break": true
      },
      {
        "text": "even your visitation, has come;",
        "break": true
      },
      {
        "text": "now is the time of their confusion.",
        "break": true
      }
    ]
  },
  {
    "book": "MIC",
    "chapter": 7,
    "verse": 5,
    "content": [
      {
        "text": "Don’t trust in a neighbor.",
        "break": true
      },
      {
        "text": "Don’t put confidence in a friend.",
        "break": true
      },
      {
        "text": "With the woman lying in your embrace,",
        "break": true
      },
      {
        "text": "be careful of the words of your mouth!",
        "break": true
      }
    ]
  },
  {
    "book": "MIC",
    "chapter": 7,
    "verse": 6,
    "content": [
      {
        "text": "For the son dishonors the father,",
        "break": true
      },
      {
        "text": "the daughter rises up against her mother,",
        "break": true
      },
      {
        "text": "the daughter-in-law against her mother-in-law;",
        "break": true
      },
      {
        "text": "a man’s enemies are the men of his own house.",
        "break": true
      }
    ]
  },
  {
    "book": "MIC",
    "chapter": 7,
    "verse": 7,
    "content": [
      {
        "text": "But as for me, I will look to Yahweh.",
        "break": true
      },
      {
        "text": "I will wait for the God of my salvation.",
        "break": true
      },
      {
        "text": "My God will hear me.",
        "break": true
      }
    ]
  },
  {
    "book": "MIC",
    "chapter": 7,
    "verse": 8,
    "content": [
      {
        "text": "Don’t rejoice against me, my enemy.",
        "break": true
      },
      {
        "text": "When I fall, I will arise.",
        "break": true
      },
      {
        "text": "When I sit in darkness, Yahweh will be a light to me.",
        "break": true
      }
    ]
  },
  {
    "book": "MIC",
    "chapter": 7,
    "verse": 9,
    "content": [
      {
        "text": "I will bear the indignation of Yahweh,",
        "break": true
      },
      {
        "text": "because I have sinned against him,",
        "break": true
      },
      {
        "text": "until he pleads my case and executes judgment for me.",
        "break": true
      },
      {
        "text": "He will bring me out to the light.",
        "break": true
      },
      {
        "text": "I will see his righteousness.",
        "break": true
      }
    ]
  },
  {
    "book": "MIC",
    "chapter": 7,
    "verse": 10,
    "content": [
      {
        "text": "Then my enemy will see it,",
        "break": true
      },
      {
        "text": "and shame will cover her who said to me,",
        "break": true
      },
      {
        "text": "“Where is Yahweh your God?”",
        "break": true
      },
      {
        "text": "My eyes will see her.",
        "break": true
      },
      {
        "text": "Now she will be trodden down like the mire of the streets.",
        "break": true
      }
    ]
  },
  {
    "book": "MIC",
    "chapter": 7,
    "verse": 11,
    "content": [
      {
        "text": "A day to build your walls!",
        "break": true
      },
      {
        "text": "In that day, he will extend your boundary.",
        "break": true
      }
    ]
  },
  {
    "book": "MIC",
    "chapter": 7,
    "verse": 12,
    "content": [
      {
        "text": "In that day they will come to you from Assyria and the cities of Egypt,",
        "break": true
      },
      {
        "text": "and from Egypt even to the River,",
        "break": true
      },
      {
        "text": "and from sea to sea,",
        "break": true
      },
      {
        "text": "and mountain to mountain.",
        "break": true
      }
    ]
  },
  {
    "book": "MIC",
    "chapter": 7,
    "verse": 13,
    "content": [
      {
        "text": "Yet the land will be desolate because of those who dwell therein,",
        "break": true
      },
      {
        "text": "for the fruit of their doings.",
        "break": true
      }
    ]
  },
  {
    "book": "MIC",
    "chapter": 7,
    "verse": 14,
    "content": [
      {
        "text": "Shepherd your people with your staff,",
        "break": true
      },
      {
        "text": "the flock of your heritage,",
        "break": true
      },
      {
        "text": "who dwell by themselves in a forest.",
        "break": true
      },
      {
        "text": "Let them feed in the middle of fertile pasture land,",
        "break": true
      },
      {
        "text": "in Bashan and Gilead, as in the days of old.",
        "break": true
      }
    ]
  },
  {
    "book": "MIC",
    "chapter": 7,
    "verse": 15,
    "content": [
      {
        "text": "“As in the days of your coming out of the land of Egypt,",
        "break": true
      },
      {
        "text": "I will show them marvelous things.”",
        "break": true
      }
    ]
  },
  {
    "book": "MIC",
    "chapter": 7,
    "verse": 16,
    "content": [
      {
        "text": "The nations will see and be ashamed of all their might.",
        "break": true
      },
      {
        "text": "They will lay their hand on their mouth.",
        "break": true
      },
      {
        "text": "Their ears will be deaf.",
        "break": true
      }
    ]
  },
  {
    "book": "MIC",
    "chapter": 7,
    "verse": 17,
    "content": [
      {
        "text": "They will lick the dust like a serpent.",
        "break": true
      },
      {
        "text": "Like crawling things of the earth, they will come trembling out of their dens.",
        "break": true
      },
      {
        "text": "They will come with fear to Yahweh our God,",
        "break": true
      },
      {
        "text": "and will be afraid because of you.",
        "break": true
      }
    ]
  },
  {
    "book": "MIC",
    "chapter": 7,
    "verse": 18,
    "content": [
      {
        "text": "Who is a God like you, who pardons iniquity,",
        "break": true
      },
      {
        "text": "and passes over the disobedience of the remnant of his heritage?",
        "break": true
      },
      {
        "text": "He doesn’t retain his anger forever,",
        "break": true
      },
      {
        "text": "because he delights in loving kindness.",
        "break": true
      }
    ]
  },
  {
    "book": "MIC",
    "chapter": 7,
    "verse": 19,
    "content": [
      {
        "text": "He will again have compassion on us.",
        "break": true
      },
      {
        "text": "He will tread our iniquities under foot.",
        "break": true
      },
      {
        "text": "You will cast all their sins into the depths of the sea.",
        "break": true
      }
    ]
  },
  {
    "book": "MIC",
    "chapter": 7,
    "verse": 20,
    "content": [
      {
        "text": "You will give truth to Jacob,",
        "break": true
      },
      {
        "text": "and mercy to Abraham,",
        "break": true
      },
      "as you have sworn to our fathers from the days of old."
    ]
  }
]